{"base":{"symbol":"USD","sign":"$"},"coin":{"id":3,"uuid":"-l8Mn2pVlRs-p","slug":"xrp-xrp","symbol":"XRP","name":"XRP","description":"<p>Ripple is both a digital currency (XRP) and an open payment network within which that currency is transferred. Ripple connects banks from all around the world, to provide immediate cross-border transactions with fewer intermediaries. Ripple aims to provide both parties an end-to-end visibility throughout the transactions. The main purpose of XRP is to make it possible to exchange cryptocurrencies and fiat.</p>\n<h3>The goal of XRP</h3>\n<p>XRP is built on bitcoin’s decentralized digital currency approach. XRP aims to be a payment ecosystem, providing a low commission currency exchange with fast international transactions.</p>\n<h3>Who started XRP</h3>\n<p>XRP was first released in 2012 by a company named OpenCoin, with co-founders CEO Chris Larsen and CTO Jed McCaleb. Both co-founders have a background in bitcoin, as well as the other developers working on the XRP protocol.</p>","color":"#000000","iconType":"vector","iconUrl":"https://cdn.coinranking.com/B1oPuTyfX/xrp.svg","websiteUrl":"https://ripple.com","socials":[{"name":"ripple","url":"https://twitter.com/ripple","type":"twitter"},{"name":"r/ripple","url":"https://www.reddit.com/r/ripple/","type":"reddit"},{"name":"ripplevideo1","url":"https://www.youtube.com/user/ripplevideo1","type":"youtube"},{"name":"Facebook","url":"https://www.facebook.com/ripplepay","type":"facebook"},{"name":"interledger/five-bells-demo","url":"https://github.com/interledger/five-bells-demo","type":"github"}],"links":[{"name":"ripple.com","type":"website","url":"https://ripple.com"},{"name":"ripple","url":"https://twitter.com/ripple","type":"twitter"},{"name":"r/ripple","url":"https://www.reddit.com/r/ripple/","type":"reddit"},{"name":"ripplevideo1","url":"https://www.youtube.com/user/ripplevideo1","type":"youtube"},{"name":"Facebook","url":"https://www.facebook.com/ripplepay","type":"facebook"},{"name":"interledger/five-bells-demo","url":"https://github.com/interledger/five-bells-demo","type":"github"}],"confirmedSupply":true,"numberOfMarkets":875,"numberOfExchanges":209,"type":"coin","volume":10245049828,"marketCap":50884912959,"price":"2.9340048154244904","circulatingSupply":44073177235,"totalSupply":99990980257,"approvedSupply":true,"firstSeen":1421798400000,"listedAt":1421798400,"change":8.18,"rank":4,"history":["3.2109896981023467","3.1679624361477754","3.0412439387018644","3.084429602631431","3.1643471736356115","3.0956808399677187","3.004946434548265","3.12544478657365","3.0768753745902955","2.995768939716095","2.932288595883511","2.8916177530586067","2.8340456435952097","2.8703214278332285","2.8223009503455785","2.792102330176881","2.933941128549866","2.9685616338667544","2.9996127885570005","3.0746331043988113","3.0008419098932397","3.057977939857607","3.101615285059375","3.0158246062746326","3.1002375370042596","3.054664045210297","2.9340048154244904"],"allTimeHigh":{"price":"3.1592207876597747","timestamp":1515369600000},"penalty":false}}